JavaWebAnquan/README.md
JavaWebAnquan/__init__.py
JavaWebAnquan/__main__.py
JavaWebAnquan/file.epub
JavaWebAnquan/index.html
JavaWebAnquan/css/__init__.py
JavaWebAnquan/css/annotations.css
JavaWebAnquan/css/main.css
JavaWebAnquan/css/normalize.css
JavaWebAnquan/css/popup.css
JavaWebAnquan/font/__init__.py
JavaWebAnquan/font/fontello.eot
JavaWebAnquan/font/fontello.svg
JavaWebAnquan/font/fontello.ttf
JavaWebAnquan/font/fontello.woff
JavaWebAnquan/img/__init__.py
JavaWebAnquan/img/annotator-glyph-sprite.png
JavaWebAnquan/img/annotator-icon-sprite.png
JavaWebAnquan/img/apple-touch-icon.png
JavaWebAnquan/img/cancelfullscreen.png
JavaWebAnquan/img/close.png
JavaWebAnquan/img/fullscreen.png
JavaWebAnquan/img/loader.gif
JavaWebAnquan/img/menu-icon.png
JavaWebAnquan/img/save.png
JavaWebAnquan/img/saved.png
JavaWebAnquan/img/settings-s.png
JavaWebAnquan/img/settings.png
JavaWebAnquan/img/star.png
JavaWebAnquan/js/__init__.py
JavaWebAnquan/js/epub.js
JavaWebAnquan/js/epub.min.js
JavaWebAnquan/js/epub.min.map
JavaWebAnquan/js/hooks.min.js
JavaWebAnquan/js/hooks.min.map
JavaWebAnquan/js/reader.js
JavaWebAnquan/js/reader.js.map
JavaWebAnquan/js/reader.min.js
JavaWebAnquan/js/reader.min.map
JavaWebAnquan/js/hooks/__init__.py
JavaWebAnquan/js/hooks/extensions/__init__.py
JavaWebAnquan/js/hooks/extensions/highlight.js
JavaWebAnquan/js/libs/__init__.py
JavaWebAnquan/js/libs/jquery.min.js
JavaWebAnquan/js/libs/localforage.min.js
JavaWebAnquan/js/libs/screenfull.js
JavaWebAnquan/js/libs/screenfull.min.js
JavaWebAnquan/js/libs/zip.min.js
JavaWebAnquan/js/plugins/__init__.py
JavaWebAnquan/js/plugins/hypothesis.js
JavaWebAnquan/js/plugins/search.js
java_web_anquan-2024.3.4.0.dist-info/METADATA
java_web_anquan-2024.3.4.0.dist-info/WHEEL
java_web_anquan-2024.3.4.0.dist-info/entry_points.txt
java_web_anquan-2024.3.4.0.dist-info/top_level.txt
java_web_anquan-2024.3.4.0.dist-info/RECORD
